permhash/__init__.py
permhash/functions.py
permhash/helpers.py
permhash/scripts/__init__.py
permhash/scripts/cli.py
permhash-0.1.4.1.dist-info/LICENSE
permhash-0.1.4.1.dist-info/METADATA
permhash-0.1.4.1.dist-info/WHEEL
permhash-0.1.4.1.dist-info/entry_points.txt
permhash-0.1.4.1.dist-info/top_level.txt
permhash-0.1.4.1.dist-info/RECORD
